README.md
setup.cfg
setup.py
aluratemp/__init__.py
aluratemp/aluratemp.py
aluratemp.egg-info/PKG-INFO
aluratemp.egg-info/SOURCES.txt
aluratemp.egg-info/dependency_links.txt
aluratemp.egg-info/top_level.txt